fsds_100719/__init__.py
fsds_100719/imports.py
fsds_100719-0.2.0.dist-info/AUTHORS.rst
fsds_100719-0.2.0.dist-info/LICENSE
fsds_100719-0.2.0.dist-info/METADATA
fsds_100719-0.2.0.dist-info/WHEEL
fsds_100719-0.2.0.dist-info/top_level.txt
fsds_100719-0.2.0.dist-info/RECORD
