Metadata-Version: 2.1
Name: fsds-100719
Version: 0.2.0
Summary: Tools for Flatiron 100719 cohorts
Home-page: https://github.com/jirvingphd/fsds_100719
Author: James Irving
Author-email: james.irving.phd@outlook.com
License: GNU General Public License v3
Keywords: fsds_100719
Platform: UNKNOWN
Classifier: Development Status :: 2 - Pre-Alpha
Classifier: Intended Audience :: Developers
Classifier: License :: OSI Approved :: GNU General Public License v3 (GPLv3)
Classifier: Natural Language :: English
Classifier: Programming Language :: Python :: 2
Classifier: Programming Language :: Python :: 2.7
Classifier: Programming Language :: Python :: 3
Classifier: Programming Language :: Python :: 3.5
Classifier: Programming Language :: Python :: 3.6
Classifier: Programming Language :: Python :: 3.7
Requires-Python: >=2.7, !=3.0.*, !=3.1.*, !=3.2.*, !=3.3.*, !=3.4.*
Requires-Dist: numpy
Requires-Dist: pandas
Requires-Dist: seaborn
Requires-Dist: matplotlib
Requires-Dist: scikit-learn
Requires-Dist: scipy
Requires-Dist: IPython
Requires-Dist: pprint
Requires-Dist: plotly (==3.10.0)
Requires-Dist: cufflinks (==0.16)
Requires-Dist: pyperclip
